taurex_cupy/__init__.py
taurex_cupy/mpi.py
taurex_cupy/spectral.py
taurex_cupy/util.py
taurex_cupy/cia/__init__.py
taurex_cupy/cia/cudacia.py
taurex_cupy/contributions/__init__.py
taurex_cupy/contributions/absorption.py
taurex_cupy/contributions/cia.py
taurex_cupy/contributions/cudacontrib.py
taurex_cupy/contributions/flatmie.py
taurex_cupy/contributions/leemie.py
taurex_cupy/contributions/rayleigh.py
taurex_cupy/contributions/simpleclouds.py
taurex_cupy/model/__init__.py
taurex_cupy/model/directimage.py
taurex_cupy/model/eclipse.py
taurex_cupy/model/transit.py
taurex_cupy/opacity/__init__.py
taurex_cupy/opacity/cudacache.py
taurex_cupy/opacity/cudaopacity.py
taurex_cupy-0.0.2.dist-info/LICENSE
taurex_cupy-0.0.2.dist-info/METADATA
taurex_cupy-0.0.2.dist-info/WHEEL
taurex_cupy-0.0.2.dist-info/entry_points.txt
taurex_cupy-0.0.2.dist-info/top_level.txt
taurex_cupy-0.0.2.dist-info/RECORD
