Metadata-Version: 2.2
Name: taurex-cupy
Version: 0.0.2
Summary: GPU acceleration of TauREx using CuPy
Author-email: "Ahmed F. Al-Refaie" <ahmed.al-refaie@ucl.ac.uk>
Project-URL: Homepage, https://ucl-exoplanets.github.io/taurex-cupy/
Project-URL: Repository, https://github.com/ucl-exoplanets/taurex-cupy
Project-URL: Documentation, https://ucl-exoplanets.github.io/taurex-cupy/
Keywords: python
Classifier: Intended Audience :: Developers
Classifier: Programming Language :: Python
Classifier: Programming Language :: Python :: 3
Classifier: Programming Language :: Python :: 3.9
Classifier: Programming Language :: Python :: 3.10
Classifier: Programming Language :: Python :: 3.11
Classifier: Programming Language :: Python :: 3.12
Classifier: Programming Language :: Python :: 3.13
Classifier: Topic :: Software Development :: Libraries :: Python Modules
Classifier: Intended Audience :: Developers
Classifier: Intended Audience :: Science/Research
Classifier: License :: OSI Approved :: BSD License
Classifier: Operating System :: Microsoft :: Windows
Classifier: Operating System :: POSIX
Classifier: Operating System :: POSIX :: Linux
Classifier: Operating System :: Unix
Classifier: Operating System :: OS Independent
Classifier: Programming Language :: Python
Classifier: Topic :: Scientific/Engineering
Classifier: Topic :: Software Development :: Libraries
Classifier: Environment :: GPU
Classifier: Environment :: GPU :: NVIDIA CUDA
Requires-Python: <4.0,>=3.9
License-File: LICENSE
Requires-Dist: cupy>=13.3.0
Requires-Dist: numpy>=1.26.4
Requires-Dist: scipy>=1.13.1
Requires-Dist: taurex>=3.2.0
